lupl/__init__.py
lupl/compose_router.py
lupl/ichunk.py
lupl/pydantic_tools/curry_model.py
lupl/pydantic_tools/mutual_constraint_validator.py
lupl/pydantic_tools/flat_init/flat_init_model.py
lupl/pydantic_tools/flat_init/utils.py
lupl-0.1.2.dist-info/METADATA
lupl-0.1.2.dist-info/WHEEL
lupl-0.1.2.dist-info/RECORD
